MANIFEST.in
NEWS.rst
README.rst
setup.py
pypolibox.egg-info/PKG-INFO
pypolibox.egg-info/SOURCES.txt
pypolibox.egg-info/dependency_links.txt
pypolibox.egg-info/entry_points.txt
pypolibox.egg-info/not-zip-safe
pypolibox.egg-info/requires.txt
pypolibox.egg-info/top_level.txt
src/pypolibox/__init__.py
src/pypolibox/avm.sty
src/pypolibox/database.py
src/pypolibox/debug.py
src/pypolibox/facts.py
src/pypolibox/hlds.py
src/pypolibox/lexicalization.py
src/pypolibox/lexicalize_messageblocks.py
src/pypolibox/messages.py
src/pypolibox/propositions.py
src/pypolibox/pypolibox.py
src/pypolibox/realization.py
src/pypolibox/rules.py
src/pypolibox/textplan.py
src/pypolibox/util.py
src/pypolibox/data/books.sqlite
src/pypolibox/grammar/build.xml
src/pypolibox/grammar/dict.xml
src/pypolibox/grammar/grammar.xml
src/pypolibox/grammar/lexicon.xml
src/pypolibox/grammar/morph.xml
src/pypolibox/grammar/rules.xml
src/pypolibox/grammar/types.xml