Metadata-Version: 1.1
Name: pypolibox
Version: 1.0.1
Summary: text generation for product recommendations using OpenCCG
Home-page: https://github.com/arne-cl/pypolibox
Author: Arne Neumann
Author-email: pypolibox.programming@arne.cl
License: GPL Version 3
Keywords: linguistics nlp nlg
Platform: UNKNOWN
Classifier: Development Status :: 4 - Beta
Classifier: License :: OSI Approved :: GNU General Public License v3 (GPLv3)
Classifier: Operating System :: OS Independent
Classifier: Programming Language :: Python :: 2.7
Classifier: Topic :: Text Processing :: Linguistic
